ralph_py_cli/__init__.py
ralph_py_cli/cli.py
ralph_py_cli/utils/__init__.py
ralph_py_cli/utils/agent_runner.py
ralph_py_cli/utils/claude_runner.py
ralph_py_cli/utils/interactive.py
ralph_py_cli/utils/ralph_plan_helper.py
ralph_py_cli/utils/token_usage.py
ralph_py_cli/utils/agents/__init__.py
ralph_py_cli/utils/agents/base.py
ralph_py_cli/utils/agents/claude.py
ralph_py_cli/utils/agents/opencode.py
ralph_py_cli-0.4.2.dist-info/METADATA
ralph_py_cli-0.4.2.dist-info/WHEEL
ralph_py_cli-0.4.2.dist-info/entry_points.txt
ralph_py_cli-0.4.2.dist-info/licenses/LICENSE
ralph_py_cli-0.4.2.dist-info/RECORD
