Metadata-Version: 2.4
Name: ralph-py-cli
Version: 0.4.2
Summary: A CLI application for running Claude Code iteratively on design documents
Project-URL: Homepage, https://github.com/rdubwiley09/ralph-py-cli
Project-URL: Repository, https://github.com/rdubwiley09/ralph-py-cli
Project-URL: Issues, https://github.com/rdubwiley09/ralph-py-cli/issues
Author: Ryan Wiley
License-Expression: MIT
License-File: LICENSE
Keywords: ai,automation,claude,cli,textual,tui
Classifier: Development Status :: 3 - Alpha
Classifier: Environment :: Console
Classifier: Intended Audience :: Developers
Classifier: License :: OSI Approved :: MIT License
Classifier: Operating System :: OS Independent
Classifier: Programming Language :: Python :: 3
Classifier: Programming Language :: Python :: 3.10
Classifier: Programming Language :: Python :: 3.11
Classifier: Programming Language :: Python :: 3.12
Classifier: Topic :: Software Development :: Code Generators
Classifier: Topic :: Utilities
Requires-Python: >=3.10
Requires-Dist: pandas>=2.3.3
Requires-Dist: pip-audit>=2.10.0
Requires-Dist: playwright>=1.57.0
Requires-Dist: textual>=0.50.0
Requires-Dist: typer>=0.12.0
